leftpad.py
leftpad-0.1.2.dist-info/METADATA
leftpad-0.1.2.dist-info/RECORD
leftpad-0.1.2.dist-info/WHEEL
leftpad-0.1.2.dist-info/top_level.txt
