Metadata-Version: 2.1
Name: leftpad
Version: 0.1.2
Summary: A port of the infamous left-pad npm package
Home-page: https://github.com/cglwn/leftpad-pypi
Author: James Cagalawan
Author-email: james.cagalawan@gmail.com
License: UNKNOWN
Platform: UNKNOWN
Classifier: Programming Language :: Python :: 3
Classifier: Operating System :: OS Independent
